.DS_Store
autom8/__init__.py
autom8/candidate.py
autom8/categories.py
autom8/cleaning.py
autom8/compare.py
autom8/context.py
autom8/csv_utils.py
autom8/docstrings.py
autom8/evaluate.py
autom8/exceptions.py
autom8/fit.py
autom8/formats.py
autom8/inference.py
autom8/main.py
autom8/matrix.py
autom8/packager.py
autom8/parsing.py
autom8/pipeline.py
autom8/preprocessors.py
autom8/receiver.py
autom8/selector.py
autom8-0.0.11.dist-info/LICENSE
autom8-0.0.11.dist-info/METADATA
autom8-0.0.11.dist-info/WHEEL
autom8-0.0.11.dist-info/top_level.txt
autom8-0.0.11.dist-info/zip-safe
autom8-0.0.11.dist-info/RECORD
